setup.py
tensorflow.py
redhat_tensorflow.egg-info/PKG-INFO
redhat_tensorflow.egg-info/SOURCES.txt
redhat_tensorflow.egg-info/dependency_links.txt
redhat_tensorflow.egg-info/top_level.txt