Metadata-Version: 1.0
Name: redhat-tensorflow
Version: 0.0.0
Summary: A build of TensorFlow by Red Hat
Home-page: https://github.com/thoth-station/
Author: UNKNOWN
Author-email: UNKNOWN
License: UNKNOWN
Platform: UNKNOWN
